{"created_at": "2024-08-20 04:12:40.148855+0000", "timetable": [{"language": "SUB", "raw_name": "isekai-shikkaku", "clean_name": "Isekai Shikkaku", "episode": "7", "datetime": "2024-08-20T16:00+01:00", "mal_id": "52367"}, {"language": "DUB", "raw_name": "isekai-shikkaku", "clean_name": "Isekai Shikkaku", "episode": "4", "datetime": "2024-08-20T20:30+01:00", "mal_id": "52367"}, {"language": "DUB", "raw_name": "helck", "clean_name": "Helck", "episode": "21", "datetime": "2024-08-20T18:00+01:00", "mal_id": "51020"}, {"language": "DUB", "raw_name": "lv-1-maou-to-one-room-yuusha", "clean_name": "Lv1 Maou to One Room Yuusha", "episode": "1", "datetime": "2024-08-20T18:00+01:00", "mal_id": "51458"}, {"language": "SUB", "raw_name": "katsute-mahou-shoujo-to-aku-wa-tekitai-shiteita", "clean_name": "Katsute Mahou Shoujo to Aku wa Tekitai shiteita.", "episode": "7", "datetime": "2024-08-20T15:45+01:00", "mal_id": "57217"}, {"language": "SUB", "raw_name": "tasuuketsu", "clean_name": "Tasuuketsu", "episode": "6", "datetime": "2024-08-20T20:00+01:00", "mal_id": "57945"}, {"language": "SUB", "raw_name": "egumi-legacy", "clean_name": "Egumi Legacy", "episode": "7", "datetime": "2024-08-20T16:00+01:00", "mal_id": "58926"}, {"language": "DUB", "raw_name": "mato-seihei-no-slave", "clean_name": "Mato Seihei no Slave", "episode": "4", "datetime": "2024-08-19T18:00+01:00", "mal_id": "50392"}, {"language": "SUB", "raw_name": "ookami-to-koushinryou-shinsaku-anime", "clean_name": "Ookami to Koushinryou: Merchant Meets the Wise Wolf", "episode": "20", "datetime": "2024-08-19T19:00+01:00", "mal_id": "51122"}, {"language": "DUB", "raw_name": "ookami-to-koushinryou-shinsaku-anime", "clean_name": "Ookami to Koushinryou: Merchant Meets the Wise Wolf", "episode": "19", "datetime": "2024-08-19T21:30+01:00", "mal_id": "51122"}, {"language": "SUB", "raw_name": "shinmai-ossan-boukensha-saikyou-party-ni-shinu-hodo-kitaerarete-muteki-ni-naru", "clean_name": "Shinmai Ossan Boukensha, Saikyou Party ni Shinu hodo Kitaerarete Muteki ni Naru.", "episode": "7", "datetime": "2024-08-19T18:30+01:00", "mal_id": "54913"}, {"language": "DUB", "raw_name": "yozakura-san-chi-no-daisakusen", "clean_name": "Yozakura-san Chi no Daisakusen", "episode": "10", "datetime": "2024-08-19T09:30+01:00", "mal_id": "53865"}, {"language": "SUB", "raw_name": "mayonaka-punch", "clean_name": "Mayonaka Punch", "episode": "7", "datetime": "2024-08-19T15:00+01:00", "mal_id": "57947"}, {"language": "SUB", "raw_name": "shy-2nd-season", "clean_name": "SHY 2nd Season", "episode": "7", "datetime": "2024-08-19T17:00+01:00", "mal_id": "57567"}, {"language": "DUB", "raw_name": "shy-2nd-season", "clean_name": "SHY 2nd Season", "episode": "6", "datetime": "2024-08-19T21:00+01:00", "mal_id": "57567"}, {"language": "SUB", "raw_name": "tokidoki-bosotto-russiago-de-dereru-tonari-no-alya-san", "clean_name": "Tokidoki Bosotto Russiago de Dereru Tonari no Alya-san", "episode": "8", "datetime": "2024-08-21T16:00+01:00", "mal_id": "54744"}, {"language": "DUB", "raw_name": "tokidoki-bosotto-russiago-de-dereru-tonari-no-alya-san", "clean_name": "Tokidoki Bosotto Russiago de Dereru Tonari no Alya-san", "episode": "5", "datetime": "2024-08-21T20:00+01:00", "mal_id": "54744"}, {"language": "SUB", "raw_name": "oshi-no-ko-season-2", "clean_name": "[Oshi no Ko] 2nd Season", "episode": "8", "datetime": "2024-08-21T16:00+01:00", "mal_id": "55791"}, {"language": "DUB", "raw_name": "nozomanu-fushi-no-boukensha", "clean_name": "Nozomanu Fushi no Boukensha", "episode": "5", "datetime": "2024-08-21T23:30+01:00", "mal_id": "51648"}, {"language": "SUB", "raw_name": "maougun-saikyou-no-majutsushi-wa-ningen-datta", "clean_name": "Maou Gun Saikyou no Majutsushi wa Ningen datta", "episode": "9", "datetime": "2024-08-21T15:00+01:00", "mal_id": "57876"}, {"language": "SUB", "raw_name": "shikanoko-nokonoko-koshitantan", "clean_name": "Shikanoko Nokonoko Koshitantan", "episode": "8", "datetime": "2024-08-21T15:31+01:00", "mal_id": "58426"}, {"language": "DUB", "raw_name": "shikanoko-nokonoko-koshitantan", "clean_name": "Shikanoko Nokonoko Koshitantan", "episode": "8", "datetime": "2024-08-21T16:00+01:00", "mal_id": "58426"}, {"language": "SUB", "raw_name": "kimi-to-boku-no-saigo-no-senjou-aruiwa-sekai-ga-hajimaru-seisen-zoku-hen", "clean_name": "Kimi to Boku no Saigo no Senjou, Aruiwa Sekai ga Hajimaru Seisen Season II", "episode": "5", "datetime": "2024-08-21T15:30+01:00", "mal_id": "49981"}, {"language": "SUB", "raw_name": "koi-wa-futago-de-warikirenai", "clean_name": "Koi wa Futago de Warikirenai", "episode": "7", "datetime": "2024-08-21T16:15+01:00", "mal_id": "55996"}, {"language": "SUB", "raw_name": "delicos-nursery", "clean_name": "Delico's Nursery", "episode": "3", "datetime": "2024-08-21T18:00+01:00", "mal_id": "56179"}, {"language": "SUB", "raw_name": "sengoku-youko-senma-konton-hen", "clean_name": "Sengoku Youko: Senma Konton-hen", "episode": "6", "datetime": "2024-08-21T16:30+01:00", "mal_id": "58488"}, {"language": "SUB", "raw_name": "yeosingangnim", "clean_name": "Yeosin Gangnim", "episode": "3", "datetime": "2024-08-21T17:31+01:00", "mal_id": "57192"}, {"language": "DUB", "raw_name": "boushoku-no-berserk", "clean_name": "Boushoku no Berserk", "episode": "4", "datetime": "2024-08-22T00:15+01:00", "mal_id": "53439"}, {"language": "SUB", "raw_name": "hazurewaku-no-joutai-ijou-skill-de-saikyou-ni-natta-ore-ga-subete-wo-juurin-suru-made", "clean_name": "Hazure Waku no [Joutai Ijou Skill] de Saikyou ni Natta Ore ga Subete wo Juurin Suru made", "episode": "7", "datetime": "2024-08-22T19:00+01:00", "mal_id": "57892"}, {"language": "SUB", "raw_name": "ore-wa-subete-wo-parry-suru-gyaku-kanchigai-no-sekai-saikyou-wa-boukensha-ni-naritai", "clean_name": "Ore wa Subete wo \"Parry\" suru: Gyaku Kanchigai no Sekai Saikyou wa Boukensha ni Naritai", "episode": "8", "datetime": "2024-08-22T16:01+01:00", "mal_id": "57058"}, {"language": "SUB", "raw_name": "gimai-seikatsu", "clean_name": "Gimai Seikatsu", "episode": "8", "datetime": "2024-08-22T13:30+01:00", "mal_id": "52481"}, {"language": "DUB", "raw_name": "suicide-squad-isekai", "clean_name": "Suicide Squad Isekai", "episode": "10", "datetime": "2024-08-22T15:00+01:00", "mal_id": "55848"}, {"language": "DUB", "raw_name": "kimi-to-boku-no-saigo-no-senjou-aruiwa-sekai-ga-hajimaru-seisen-zoku-hen", "clean_name": "Kimi to Boku no Saigo no Senjou, Aruiwa Sekai ga Hajimaru Seisen Season II", "episode": "5", "datetime": "2024-08-22T22:30+01:00", "mal_id": "49981"}, {"language": "SUB", "raw_name": "giji-harem", "clean_name": "Giji Harem", "episode": "8", "datetime": "2024-08-22T17:30+01:00", "mal_id": "54968"}, {"language": "DUB", "raw_name": "bartender-kami-no-glass", "clean_name": "Bartender: Kami no Glass", "episode": "5", "datetime": "2024-08-22T22:00+01:00", "mal_id": "53407"}, {"language": "SUB", "raw_name": "senpai-wa-otokonoko", "clean_name": "Senpai wa Otokonoko", "episode": "7", "datetime": "2024-08-22T19:30+01:00", "mal_id": "54855"}, {"language": "SUB", "raw_name": "megami-no-caf-terrace-season-2", "clean_name": "Megami no Caf\u00e9 Terrace Season 2", "episode": "8", "datetime": "2024-08-22T18:30+01:00", "mal_id": "55749"}, {"language": "SUB", "raw_name": "tasogare-outfocus", "clean_name": "Tasogare Outfocus", "episode": "8", "datetime": "2024-08-22T16:00+01:00", "mal_id": "55844"}, {"language": "DUB", "raw_name": "tasogare-outfocus", "clean_name": "Tasogare Outfocus", "episode": "6", "datetime": "2024-08-22T20:30+01:00", "mal_id": "55844"}, {"language": "SUB", "raw_name": "ramen-akaneko", "clean_name": "Ramen Aka Neko", "episode": "8", "datetime": "2024-08-22T17:00+01:00", "mal_id": "57325"}, {"language": "SUB", "raw_name": "bishoujo-senshi-sailor-moon-cosmos-1", "clean_name": "Bishoujo Senshi Sailor Moon Cosmos", "episode": "1", "datetime": "2024-08-22T08:00+01:00", "mal_id": "51716"}, {"language": "DUB", "raw_name": "bishoujo-senshi-sailor-moon-cosmos-1", "clean_name": "Bishoujo Senshi Sailor Moon Cosmos", "episode": "1", "datetime": "2024-08-22T08:00+01:00", "mal_id": "51716"}, {"language": "SUB", "raw_name": "tensei-shitara-slime-datta-ken-3rd-season", "clean_name": "Tensei shitara Slime Datta Ken 3", "episode": "19", "datetime": "2024-08-23T16:30+01:00", "mal_id": "53580"}, {"language": "DUB", "raw_name": "tensei-shitara-slime-datta-ken-3rd-season", "clean_name": "Tensei shitara Slime Datta Ken 3", "episode": "18", "datetime": "2024-08-23T22:30+01:00", "mal_id": "53580"}, {"language": "DUB", "raw_name": "maou-gakuin-no-futekigousha-2-part-2", "clean_name": "Maou Gakuin no Futekigousha 2 Part 2", "episode": "12", "datetime": "2024-08-23T21:30+01:00", "mal_id": "48418"}, {"language": "DUB", "raw_name": "sokushi-cheat-ga-saikyou-sugite-isekai-no-yatsura-ga-marude-aite-ni-naranai-n-desu-ga", "clean_name": "Sokushi Cheat ga Saikyou sugite, Isekai no Yatsura ga Marude Aite ni Naranai n desu ga.", "episode": "6", "datetime": "2024-08-23T18:00+01:00", "mal_id": "53730"}, {"language": "SUB", "raw_name": "2-5-jigen-no-ririsa", "clean_name": "2.5-jigen no Ririsa", "episode": "8", "datetime": "2024-08-23T14:31+01:00", "mal_id": "53802"}, {"language": "SUB", "raw_name": "bye-bye-earth", "clean_name": "Bye Bye, Earth", "episode": "7", "datetime": "2024-08-23T16:00+01:00", "mal_id": "53626"}, {"language": "DUB", "raw_name": "bye-bye-earth", "clean_name": "Bye Bye, Earth", "episode": "5", "datetime": "2024-08-23T23:00+01:00", "mal_id": "53626"}, {"language": "SUB", "raw_name": "kono-sekai-wa-fukanzen-sugiru", "clean_name": "Kono Sekai wa Fukanzen Sugiru", "episode": "8", "datetime": "2024-08-23T19:30+01:00", "mal_id": "54835"}, {"language": "DUB", "raw_name": "kono-sekai-wa-fukanzen-sugiru", "clean_name": "Kono Sekai wa Fukanzen Sugiru", "episode": "8", "datetime": "2024-08-23T19:30+01:00", "mal_id": "54835"}, {"language": "SUB", "raw_name": "dungeon-no-naka-no-hito", "clean_name": "Dungeon no Naka no Hito", "episode": "7", "datetime": "2024-08-23T18:30+01:00", "mal_id": "56348"}, {"language": "SUB", "raw_name": "nier-automata-ver1-1a-part-2", "clean_name": "NieR:Automata Ver1.1a Part 2", "episode": "7", "datetime": "2024-08-23T17:00+01:00", "mal_id": "56063"}, {"language": "DUB", "raw_name": "nier-automata-ver1-1a-part-2", "clean_name": "NieR:Automata Ver1.1a Part 2", "episode": "4", "datetime": "2024-08-23T21:00+01:00", "mal_id": "56063"}, {"language": "SUB", "raw_name": "code-geass-dakkan-no-z", "clean_name": "Code Geass: Dakkan no Roz\u00e9", "episode": "10", "datetime": "2024-08-23T08:01+01:00", "mal_id": "56835"}, {"language": "DUB", "raw_name": "code-geass-dakkan-no-z", "clean_name": "Code Geass: Dakkan no Roz\u00e9", "episode": "10", "datetime": "2024-08-23T08:01+01:00", "mal_id": "56835"}, {"language": "SUB", "raw_name": "dead-dead-demons-dededede-destruction-ona", "clean_name": "Dead Dead Demons Dededede Destruction (ONA)", "episode": "14", "datetime": "2024-08-23T04:01+01:00", "mal_id": "58883"}, {"language": "DUB", "raw_name": "dead-dead-demons-dededede-destruction-ona", "clean_name": "Dead Dead Demons Dededede Destruction (ONA)", "episode": "14", "datetime": "2024-08-23T04:01+01:00", "mal_id": "58883"}, {"language": "SUB", "raw_name": "ninjala", "clean_name": "Ninjala", "episode": "131", "datetime": "2024-08-23T03:30+01:00", "mal_id": "50418"}, {"language": "SUB", "raw_name": "boku-no-hero-academia-7", "clean_name": "Boku no Hero Academia 7", "episode": "14", "datetime": "2024-08-24T10:30+01:00", "mal_id": "54789"}, {"language": "DUB", "raw_name": "boku-no-hero-academia-7", "clean_name": "Boku no Hero Academia 7", "episode": "14", "datetime": "2024-08-24T20:00+01:00", "mal_id": "54789"}, {"language": "SUB", "raw_name": "naze-boku-no-sekai-wo-daremo-oboeteinai-no-ka", "clean_name": "Naze Boku no Sekai wo Daremo Oboeteinai no ka?", "episode": "7", "datetime": "2024-08-24T16:15+01:00", "mal_id": "56062"}, {"language": "DUB", "raw_name": "naze-boku-no-sekai-wo-daremo-oboeteinai-no-ka", "clean_name": "Naze Boku no Sekai wo Daremo Oboeteinai no ka?", "episode": "5", "datetime": "2024-08-24T22:00+01:00", "mal_id": "56062"}, {"language": "DUB", "raw_name": "boku-no-kokoro-no-yabai-yatsu-2", "clean_name": "Boku no Kokoro no Yabai Yatsu 2", "episode": "10", "datetime": "2024-08-24T18:00+01:00", "mal_id": "55690"}, {"language": "SUB", "raw_name": "mob-kara-hajimaru-tansaku-eiyuutan", "clean_name": "Mob kara Hajimaru Tansaku Eiyuutan", "episode": "9", "datetime": "2024-08-24T15:00+01:00", "mal_id": "57646"}, {"language": "SUB", "raw_name": "madougushi-dahlia-wa-utsumukanai-kyou-kara-jiyuu-na-shokunin-life", "clean_name": "Madougushi Dahlia wa Utsumukanai: Kyou kara Jiyuu na Shokunin Life", "episode": "8", "datetime": "2024-08-24T13:30+01:00", "mal_id": "56449"}, {"language": "SUB", "raw_name": "nige-jouzu-no-wakagimi", "clean_name": "Nige Jouzu no Wakagimi", "episode": "8", "datetime": "2024-08-24T17:00+01:00", "mal_id": "54724"}, {"language": "DUB", "raw_name": "nige-jouzu-no-wakagimi", "clean_name": "Nige Jouzu no Wakagimi", "episode": "4", "datetime": "2024-08-24T20:30+01:00", "mal_id": "54724"}, {"language": "SUB", "raw_name": "make-heroine-ga-oosugiru", "clean_name": "Make Heroine ga Oosugiru!", "episode": "7", "datetime": "2024-08-24T18:00+01:00", "mal_id": "57524"}, {"language": "DUB", "raw_name": "make-heroine-ga-oosugiru", "clean_name": "Make Heroine ga Oosugiru!", "episode": "5", "datetime": "2024-08-24T21:00+01:00", "mal_id": "57524"}, {"language": "SUB", "raw_name": "shoushimin-series", "clean_name": "Shoushimin Series", "episode": "7", "datetime": "2024-08-24T19:00+01:00", "mal_id": "57810"}, {"language": "SUB", "raw_name": "detective-conan", "clean_name": "Detective Conan", "episode": "1133", "datetime": "2024-08-24T12:30+01:00", "mal_id": "235"}, {"language": "SUB", "raw_name": "atri-my-dear-moments", "clean_name": "ATRI: My Dear Moments", "episode": "7", "datetime": "2024-08-24T17:30+01:00", "mal_id": "53128"}, {"language": "SUB", "raw_name": "boku-no-tsuma-wa-kanjou-ga-nai", "clean_name": "Boku no Tsuma wa Kanjou ga Nai", "episode": "9", "datetime": "2024-08-24T16:00+01:00", "mal_id": "58272"}, {"language": "SUB", "raw_name": "the-fable", "clean_name": "The Fable", "episode": "20", "datetime": "2024-08-24T17:30+01:00", "mal_id": "55911"}, {"language": "SUB", "raw_name": "karasu-wa-aruji-wo-erabanai", "clean_name": "Karasu wa Aruji wo Erabanai", "episode": "16", "datetime": "2024-08-24T19:30+01:00", "mal_id": "56980"}, {"language": "SUB", "raw_name": "elf-san-wa-yaserarenai", "clean_name": "Elf-san wa Yaserarenai.", "episode": "8", "datetime": "2024-08-24T16:01+01:00", "mal_id": "57845"}, {"language": "SUB", "raw_name": "monogatari-series-off-and-monster-season", "clean_name": "Monogatari Series: Off & Monster Season", "episode": "7", "datetime": "2024-08-24T15:30+01:00", "mal_id": "57864"}, {"language": "SUB", "raw_name": "tensui-no-sakuna-hime", "clean_name": "Tensui no Sakuna-hime", "episode": "8", "datetime": "2024-08-24T16:30+01:00", "mal_id": "58357"}, {"language": "SUB", "raw_name": "shadowverse-flame-arc-hen", "clean_name": "Shadowverse Flame: Arc-hen", "episode": "18", "datetime": "2024-08-24T03:30+01:00", "mal_id": "57614"}, {"language": "SUB", "raw_name": "cardfight-vanguard-overdress-season-7", "clean_name": "Cardfight!! Vanguard: Divinez Season 2", "episode": "8", "datetime": "2024-08-24T00:40+01:00", "mal_id": "54143"}, {"language": "SUB", "raw_name": "one-piece", "clean_name": "One Piece", "episode": "1117", "datetime": "2024-08-25T03:00+01:00", "mal_id": "21"}, {"language": "SUB", "raw_name": "kami-no-tou-tower-of-god-2", "clean_name": "Kami no Tou 2", "episode": "8", "datetime": "2024-08-25T15:01+01:00", "mal_id": "52635"}, {"language": "DUB", "raw_name": "kami-no-tou-tower-of-god-2", "clean_name": "Kami no Tou 2", "episode": "6", "datetime": "2024-08-25T21:00+01:00", "mal_id": "52635"}, {"language": "SUB", "raw_name": "tsue-to-tsurugi-no-wistoria", "clean_name": "Tsue to Tsurugi no Wistoria", "episode": "7", "datetime": "2024-08-25T10:30+01:00", "mal_id": "58059"}, {"language": "DUB", "raw_name": "tsue-to-tsurugi-no-wistoria", "clean_name": "Tsue to Tsurugi no Wistoria", "episode": "6", "datetime": "2024-08-25T22:30+01:00", "mal_id": "58059"}, {"language": "SUB", "raw_name": "yozakura-san-chi-no-daisakusen", "clean_name": "Yozakura-san Chi no Daisakusen", "episode": "21", "datetime": "2024-08-25T09:30+01:00", "mal_id": "53865"}, {"language": "SUB", "raw_name": "isekai-yururi-kikou-kosodateshinagara-boukensha-shimasu", "clean_name": "Isekai Yururi Kikou: Kosodateshinagara Boukensha Shimasu", "episode": "9", "datetime": "2024-08-25T18:30+01:00", "mal_id": "57380"}, {"language": "DUB", "raw_name": "isekai-yururi-kikou-kosodateshinagara-boukensha-shimasu", "clean_name": "Isekai Yururi Kikou: Kosodateshinagara Boukensha Shimasu", "episode": "9", "datetime": "2024-08-25T18:30+01:00", "mal_id": "57380"}, {"language": "SUB", "raw_name": "fairy-tail-100-years-quest", "clean_name": "FAIRY TAIL: 100 YEARS QUEST", "episode": "8", "datetime": "2024-08-25T10:00+01:00", "mal_id": "49785"}, {"language": "DUB", "raw_name": "fairy-tail-100-years-quest", "clean_name": "FAIRY TAIL: 100 YEARS QUEST", "episode": "6", "datetime": "2024-08-25T22:00+01:00", "mal_id": "49785"}, {"language": "SUB", "raw_name": "vtuber-nandaga-haishin-kiri-wasuretara-densetsu-ni-natteta", "clean_name": "VTuber Nandaga Haishin Kiri Wasuretara Densetsu ni Natteta", "episode": "8", "datetime": "2024-08-25T16:30+01:00", "mal_id": "54284"}, {"language": "DUB", "raw_name": "vtuber-nandaga-haishin-kiri-wasuretara-densetsu-ni-natteta", "clean_name": "VTuber Nandaga Haishin Kiri Wasuretara Densetsu ni Natteta", "episode": "6", "datetime": "2024-08-25T23:00+01:00", "mal_id": "54284"}, {"language": "SUB", "raw_name": "holo-no-graffiti", "clean_name": "Holo no Graffiti", "episode": "275", "datetime": "2024-08-25T10:01+01:00", "mal_id": "44042"}, {"language": "SUB", "raw_name": "na-nare-hana-nare", "clean_name": "Na-Nare Hana-Nare", "episode": "8", "datetime": "2024-08-25T17:30+01:00", "mal_id": "57099"}, {"language": "SUB", "raw_name": "chibi-maruko-chan-1995", "clean_name": "Chibi Maruko-chan (1995)", "episode": "1444", "datetime": "2024-08-25T12:00+01:00", "mal_id": "6149"}, {"language": "SUB", "raw_name": "kinnikuman-shin-anime", "clean_name": "Kinnikuman: Kanpeki Choujin Shiso-hen", "episode": "8", "datetime": "2024-08-25T16:30+01:00", "mal_id": "54730"}, {"language": "SUB", "raw_name": "wonderful-precure", "clean_name": "Wonderful Precure!", "episode": "30", "datetime": "2024-08-25T02:30+01:00", "mal_id": "57390"}, {"language": "SUB", "raw_name": "yami-shibai-13", "clean_name": "Yami Shibai 13", "episode": "7", "datetime": "2024-08-25T20:45+01:00", "mal_id": "59010"}]}